measure_ai_proficiency/__init__.py
measure_ai_proficiency/__main__.py
measure_ai_proficiency/config.py
measure_ai_proficiency/github_scanner.py
measure_ai_proficiency/mcp_server.py
measure_ai_proficiency/repo_config.py
measure_ai_proficiency/reporter.py
measure_ai_proficiency/scanner.py
measure_ai_proficiency-0.5.0.dist-info/licenses/LICENSE
measure_ai_proficiency-0.5.0.dist-info/METADATA
measure_ai_proficiency-0.5.0.dist-info/WHEEL
measure_ai_proficiency-0.5.0.dist-info/entry_points.txt
measure_ai_proficiency-0.5.0.dist-info/top_level.txt
measure_ai_proficiency-0.5.0.dist-info/RECORD
