Metadata-Version: 2.4
Name: measure-ai-proficiency
Version: 0.5.0
Summary: Measure AI coding proficiency based on context engineering artifacts
Author: Peter Skoett
License: MIT
Project-URL: Homepage, https://github.com/pskoett/measuring-ai-proficiency
Project-URL: Repository, https://github.com/pskoett/measuring-ai-proficiency
Project-URL: Issues, https://github.com/pskoett/measuring-ai-proficiency/issues
Keywords: ai,coding,proficiency,context-engineering,claude,copilot,cursor,codex,developer-tools
Classifier: Development Status :: 3 - Alpha
Classifier: Environment :: Console
Classifier: Intended Audience :: Developers
Classifier: License :: OSI Approved :: MIT License
Classifier: Operating System :: OS Independent
Classifier: Programming Language :: Python :: 3
Classifier: Programming Language :: Python :: 3.10
Classifier: Programming Language :: Python :: 3.11
Classifier: Programming Language :: Python :: 3.12
Classifier: Programming Language :: Python :: 3.13
Classifier: Topic :: Software Development
Classifier: Topic :: Software Development :: Quality Assurance
Requires-Python: >=3.10
License-File: LICENSE
Requires-Dist: pyyaml>=6.0
Requires-Dist: mcp>=0.9.0
Provides-Extra: dev
Requires-Dist: pytest>=7.0; extra == "dev"
Requires-Dist: pytest-cov>=4.0; extra == "dev"
Requires-Dist: pytest-asyncio>=0.21.0; extra == "dev"
Requires-Dist: black>=23.0; extra == "dev"
Requires-Dist: ruff>=0.1.0; extra == "dev"
Requires-Dist: mypy>=1.0; extra == "dev"
Dynamic: license-file
